LICENSE
README.md
setup.py
s3_uri_to_url/__init__.py
s3_uri_to_url/main.py
s3_uri_to_url.egg-info/PKG-INFO
s3_uri_to_url.egg-info/SOURCES.txt
s3_uri_to_url.egg-info/dependency_links.txt
s3_uri_to_url.egg-info/entry_points.txt
s3_uri_to_url.egg-info/not-zip-safe
s3_uri_to_url.egg-info/requires.txt
s3_uri_to_url.egg-info/top_level.txt