Metadata-Version: 2.1
Name: s3-uri-to-url
Version: 0.1.2
Summary: s3_uri_to_url - Convert S3 URI to URL
Home-page: https://github.com/its-dron/s3-uri-to-url
Author: Daniel Ron
Author-email: dron@alum.mit.edu
License: Apache 2.0
Platform: UNKNOWN
Requires-Python: >=3.6.*
License-File: LICENSE
